arduino_rpi_taskmaster
